MANIFEST.in
README.rst
setup.cfg
setup.py
deform_bootstrap_extra/__init__.py
deform_bootstrap_extra/helpers.py
deform_bootstrap_extra/schema.py
deform_bootstrap_extra/schemaker.py
deform_bootstrap_extra/widgets.py
deform_bootstrap_extra.egg-info/PKG-INFO
deform_bootstrap_extra.egg-info/SOURCES.txt
deform_bootstrap_extra.egg-info/dependency_links.txt
deform_bootstrap_extra.egg-info/not-zip-safe
deform_bootstrap_extra.egg-info/requires.txt
deform_bootstrap_extra.egg-info/top_level.txt
deform_bootstrap_extra/jests/__init__.py
deform_bootstrap_extra/jests/test_colander.py
deform_bootstrap_extra/locale/deform_bootstrap_extra.pot
deform_bootstrap_extra/locale/pt_BR/LC_MESSAGES/deform_bootstrap_extra.mo
deform_bootstrap_extra/locale/pt_BR/LC_MESSAGES/deform_bootstrap_extra.po
deform_bootstrap_extra/pyramid/__init__.py
deform_bootstrap_extra/pyramid/views.py
deform_bootstrap_extra/static/deform_bootstrap_extra.css
deform_bootstrap_extra/static/xaja.js
deform_bootstrap_extra/static/jQuery-Tags-Input/README.md
deform_bootstrap_extra/static/jQuery-Tags-Input/example.html
deform_bootstrap_extra/static/jQuery-Tags-Input/jquery.tagsinput.css
deform_bootstrap_extra/static/jQuery-Tags-Input/jquery.tagsinput.js
deform_bootstrap_extra/static/jQuery-Tags-Input/jquery.tagsinput.min.js
deform_bootstrap_extra/static/jQuery-Tags-Input/test/fake_json_endpoint.html
deform_bootstrap_extra/static/jQuery-Tags-Input/test/fake_plaintext_endpoint.html
deform_bootstrap_extra/templates/checkbox.pt
deform_bootstrap_extra/templates/form.pt
deform_bootstrap_extra/templates/mapping_item.pt
deform_bootstrap_extra/templates/password.pt
deform_bootstrap_extra/templates/slug.pt
deform_bootstrap_extra/templates/textarea.pt
deform_bootstrap_extra/templates/textinput.pt
deform_bootstrap_extra/templates/xoxco_tags.pt
deform_bootstrap_extra/templates-modal/form.pt