Metadata-Version: 1.1
Name: deform-bootstrap-extra
Version: 0.2.8
Summary: A complement to deform_bootstrap, which offers Twitter Bootstrap compatible widgets, templates and styles for the deform form library.
Home-page: https://github.com/nandoflorestan/deform_bootstrap_extra
Author: Nando Florestan
Author-email: nandoflorestan@gmail.com
License: BSD
Keywords: twitter bootstrap deform styles css web forms form
Platform: UNKNOWN
Classifier: Development Status :: 5 - Production/Stable
Classifier: Intended Audience :: Developers
Classifier: License :: OSI Approved :: BSD License
Classifier: Environment :: Web Environment
Classifier: Framework :: Pyramid
Classifier: Operating System :: OS Independent
Classifier: Programming Language :: Python
Classifier: Programming Language :: Python :: 2.7
Classifier: Programming Language :: Python :: 3
Classifier: Programming Language :: Python :: 3.2
Classifier: Programming Language :: Python :: 3.3
Classifier: Topic :: Software Development :: Libraries :: Python Modules
